LICENSE.txt
MANIFEST.in
README.rst
setup.py
roberto/__init__.py
roberto/__main__.py
roberto/_version.py
roberto/conda.py
roberto/config.py
roberto/default_config.yaml
roberto/program.py
roberto/requirements.py
roberto/tasks.py
roberto/testenvs.py
roberto/tools.py
roberto/utils.py
roberto/venv.py
roberto/version.py
roberto.egg-info/PKG-INFO
roberto.egg-info/SOURCES.txt
roberto.egg-info/dependency_links.txt
roberto.egg-info/entry_points.txt
roberto.egg-info/requires.txt
roberto.egg-info/top_level.txt
roberto/test/__init__.py
roberto/test/test_requirements.py
roberto/test/test_utils.py