Metadata-Version: 2.1
Name: roberto
Version: 2.0.3
Summary: Collection of configurable development workflows
Home-page: https://github.com/theochem/roberto
Author: HORTON-ChemTools Dev Team
Author-email: horton.chemtools@gmail.com
Classifier: Development Status :: 5 - Production/Stable
Classifier: Environment :: Console
Classifier: License :: OSI Approved :: GNU General Public License v3 or later (GPLv3+)
Classifier: Operating System :: POSIX :: Linux
Classifier: Programming Language :: Python :: 3.6
Classifier: Programming Language :: Python :: 3.7
Classifier: Programming Language :: Python :: 3.8
Classifier: Programming Language :: Python :: 3.9
Requires-Python: >=3.6
License-File: LICENSE.txt
